mips32/mips32.v
//-------------------------------------------------------
// mips.v
// Max Yi (byyi@hmc.edu) and David_Harris@hmc.edu 12/9/03
// Model of subset of MIPS processor described in Ch 1
//
// Matsutani: ADDI instruction is added
//-------------------------------------------------------

// simplified MIPS processor
//Modified by matutani
//module mips #(parameter WIDTH = 8, REGBITS = 3)
module mips #(parameter WIDTH = 32, REGBITS = 3)
//
             (input              clk, reset, 
              input  [WIDTH-1:0] memdata, 
              output             memread, memwrite, 
              output [WIDTH-1:0] adr, writedata);

   wire [31:0] instr;
   wire        zero, alusrca, memtoreg, iord, pcen, regwrite, regdst;
   wire [1:0]  aluop,pcsource,alusrcb;
   wire [3:0]  irwrite;
   wire [2:0]  alucont;

   controller  cont(clk, reset, instr[31:26], zero, memread, memwrite, 
                    alusrca, memtoreg, iord, pcen, regwrite, regdst,
                    pcsource, alusrcb, aluop, irwrite);
   alucontrol  ac(aluop, instr[5:0], alucont);
   datapath    #(WIDTH, REGBITS) 
               dp(clk, reset, memdata, alusrca, memtoreg, iord, pcen,
                  regwrite, regdst, pcsource, alusrcb, irwrite, alucont,
                  zero, instr, adr, writedata);
endmodule

module controller(input clk, reset, 
                  input      [5:0] op, 
                  input            zero, 
                  output reg       memread, memwrite, alusrca, memtoreg, iord, 
                  output           pcen, 
                  output reg       regwrite, regdst, 
                  output reg [1:0] pcsource, alusrcb, aluop, 
                  output reg [3:0] irwrite);

   parameter   FETCH1  =  4'b0001;
   parameter   FETCH2  =  4'b0010;
   parameter   FETCH3  =  4'b0011;
   parameter   FETCH4  =  4'b0100;
   parameter   DECODE  =  4'b0101;
   parameter   MEMADR  =  4'b0110;
   parameter   LBRD    =  4'b0111;
   parameter   LBWR    =  4'b1000;
   parameter   SBWR    =  4'b1001;
   parameter   RTYPEEX =  4'b1010;
   parameter   RTYPEWR =  4'b1011;
   parameter   BEQEX   =  4'b1100;
   parameter   JEX     =  4'b1101;
   parameter   ADDIEX  =  4'b1110;
   parameter   ADDIWR  =  4'b1111;

   parameter   LB      =  6'b100000;
   parameter   SB      =  6'b101000;
   //Added by matutani
   parameter   LW      =  6'b100011;
   parameter   SW      =  6'b101011;
   //
   parameter   RTYPE   =  6'b0;
   parameter   BEQ     =  6'b000100;
   parameter   ADDI    =  6'b001000;
   parameter   J       =  6'b000010;

   reg [3:0] state, nextstate;
   reg       pcwrite, pcwritecond;

   // state register
   always @(posedge clk)
      if(reset) state <= FETCH1;
      else state <= nextstate;

   // next state logic
   always @(*)
      begin
         case(state)
            //Modified by matutani
            //FETCH1:  nextstate <= FETCH2;
            FETCH1:  nextstate <= DECODE;
            //
            FETCH2:  nextstate <= FETCH3;
            FETCH3:  nextstate <= FETCH4;
            FETCH4:  nextstate <= DECODE;
            DECODE:  case(op)
                        LB:      nextstate <= MEMADR;
                        SB:      nextstate <= MEMADR;
                        //Added by matutani
                        LW:      nextstate <= MEMADR;
                        SW:      nextstate <= MEMADR;
                        //
                        RTYPE:   nextstate <= RTYPEEX;
                        BEQ:     nextstate <= BEQEX;
                        ADDI:    nextstate <= ADDIEX;
                        J:       nextstate <= JEX;
                        default: nextstate <= FETCH1; // should never happen
                     endcase
            MEMADR:  case(op)
                        LB:      nextstate <= LBRD;
                        SB:      nextstate <= SBWR;
                        //Added by matutani
                        LW:      nextstate <= LBRD;
                        SW:      nextstate <= SBWR;
                        //
                        default: nextstate <= FETCH1; // should never happen
                     endcase
            LBRD:    nextstate <= LBWR;
            LBWR:    nextstate <= FETCH1;
            SBWR:    nextstate <= FETCH1;
            RTYPEEX: nextstate <= RTYPEWR;
            RTYPEWR: nextstate <= FETCH1;
            BEQEX:   nextstate <= FETCH1;
            JEX:     nextstate <= FETCH1;
            ADDIEX:  nextstate <= ADDIWR;
            ADDIWR:  nextstate <= FETCH1;
            default: nextstate <= FETCH1; // should never happen
         endcase
      end

   always @(*)
      begin
            // set all outputs to zero, then conditionally assert just the appropriate ones
            irwrite <= 4'b0000;
            pcwrite <= 0; pcwritecond <= 0;
            regwrite <= 0; regdst <= 0;
            memread <= 0; memwrite <= 0;
            alusrca <= 0; alusrcb <= 2'b00; aluop <= 2'b00;
            pcsource <= 2'b00;
            iord <= 0; memtoreg <= 0;
            case(state)
               FETCH1: 
                  begin
                     memread <= 1; 
                     irwrite <= 4'b1000; 
                     alusrcb <= 2'b01; 
                     pcwrite <= 1;
                  end
               FETCH2: 
                  begin
                     memread <= 1;
                     irwrite <= 4'b0100;
                     alusrcb <= 2'b01;
                     pcwrite <= 1;
                  end
               FETCH3:
                  begin
                     memread <= 1;
                     irwrite <= 4'b0010;
                     alusrcb <= 2'b01;
                     pcwrite <= 1;
                  end
               FETCH4:
                  begin
                     memread <= 1;
                     irwrite <= 4'b0001;
                     alusrcb <= 2'b01;
                     pcwrite <= 1;
                  end
               DECODE: alusrcb <= 2'b11;
               MEMADR:
                  begin
                     alusrca <= 1;
                     alusrcb <= 2'b10;
                  end
               LBRD:
                  begin
                     memread <= 1;
                     iord    <= 1;
                  end
               LBWR:
                  begin
                     regwrite <= 1;
                     memtoreg <= 1;
                  end
               SBWR:
                  begin
                     memwrite <= 1;
                     iord     <= 1;
                  end
               RTYPEEX: 
                  begin
                     alusrca <= 1;
                     aluop   <= 2'b10;
                  end
               RTYPEWR:
                  begin
                     regdst   <= 1;
                     regwrite <= 1;
                  end
               BEQEX:
                  begin
                     alusrca     <= 1;
                     aluop       <= 2'b01;
                     pcwritecond <= 1;
                     pcsource    <= 2'b01;
                  end
               JEX:
                  begin
                     pcwrite  <= 1;
                     pcsource <= 2'b10;
                  end
               ADDIEX:
                  begin
                     alusrca <= 1;
                     alusrcb <= 2'b10;
                  end
               ADDIWR:
                  begin
                     regdst   <= 0;
                     regwrite <= 1;
                  end
         endcase
      end
   assign pcen = pcwrite | (pcwritecond & zero); // program counter enable
endmodule

module alucontrol(input      [1:0] aluop, 
                  input      [5:0] funct, 
                  output reg [2:0] alucont);

   always @(*)
      case(aluop)
         2'b00: alucont <= 3'b010;  // add for lb/sb/addi
         2'b01: alucont <= 3'b110;  // sub (for beq)
         default: case(funct)       // R-Type instructions
                     6'b100000: alucont <= 3'b010; // add (for add)
                     6'b100010: alucont <= 3'b110; // subtract (for sub)
                     6'b100100: alucont <= 3'b000; // logical and (for and)
                     6'b100101: alucont <= 3'b001; // logical or (for or)
                     6'b101010: alucont <= 3'b111; // set on less (for slt)
                     default:   alucont <= 3'b101; // should never happen
                  endcase
      endcase
endmodule

module datapath #(parameter WIDTH = 8, REGBITS = 3)
                 (input              clk, reset, 
                  input  [WIDTH-1:0] memdata, 
                  input              alusrca, memtoreg, iord, pcen, regwrite, regdst,
                  input  [1:0]       pcsource, alusrcb, 
                  input  [3:0]       irwrite, 
                  input  [2:0]       alucont, 
                  output             zero, 
                  output [31:0]      instr, 
                  output [WIDTH-1:0] adr, writedata);

   // the size of the parameters must be changed to match the WIDTH parameter
   //Modified by matutani
   //parameter CONST_ZERO = 8'b0;
   //parameter CONST_ONE =  8'b1;
   parameter CONST_ZERO = 32'b0;
   parameter CONST_ONE =  32'b1;
   parameter CONST_FOUR =  32'b100;
   //

   wire [REGBITS-1:0] ra1, ra2, wa;
   wire [WIDTH-1:0]   pc, nextpc, md, rd1, rd2, wd, a, src1, src2, aluresult,
                          aluout, constx4;

   // shift left constant field by 2
   //Modified by matutani
   //assign constx4 = {instr[WIDTH-3:0],2'b00};
   assign constx4 = {instr[16-3:0],2'b00};
   //

   // register file address fields
   assign ra1 = instr[REGBITS+20:21];
   assign ra2 = instr[REGBITS+15:16];
   mux2       #(REGBITS) regmux(instr[REGBITS+15:16], instr[REGBITS+10:11], regdst, wa);

   // independent of bit width, load instruction into four 8-bit registers over four cycles
   //Modified by matutani
   //flopen     #(8)      ir0(clk, irwrite[0], memdata[7:0], instr[7:0]);
   //flopen     #(8)      ir1(clk, irwrite[1], memdata[7:0], instr[15:8]);
   //flopen     #(8)      ir2(clk, irwrite[2], memdata[7:0], instr[23:16]);
   //flopen     #(8)      ir3(clk, irwrite[3], memdata[7:0], instr[31:24]);
   flopen     #(32)      ir3(clk, irwrite[3], memdata[31:0], instr[31:0]);
   //

   // datapath
   flopenr    #(WIDTH)  pcreg(clk, reset, pcen, nextpc, pc);
   flop       #(WIDTH)  mdr(clk, memdata, md);
   flop       #(WIDTH)  areg(clk, rd1, a);	
   flop       #(WIDTH)  wrd(clk, rd2, writedata);
   flop       #(WIDTH)  res(clk, aluresult, aluout);
   mux2       #(WIDTH)  adrmux(pc, aluout, iord, adr);
   mux2       #(WIDTH)  src1mux(pc, a, alusrca, src1);
   //Modified by matutani
   //mux4       #(WIDTH)  src2mux(writedata, CONST_ONE, instr[WIDTH-1:0], 
   mux4       #(WIDTH)  src2mux(writedata, CONST_FOUR, {{16{instr[15]}},instr[15:0]}, 
                                constx4, alusrcb, src2);
   //
   mux4       #(WIDTH)  pcmux(aluresult, aluout, constx4, CONST_ZERO, pcsource, nextpc);
   mux2       #(WIDTH)  wdmux(aluout, md, memtoreg, wd);
   regfile    #(WIDTH,REGBITS) rf(clk, regwrite, ra1, ra2, wa, wd, rd1, rd2);
   alu        #(WIDTH) alunit(src1, src2, alucont, aluresult);
   zerodetect #(WIDTH) zd(aluresult, zero);
endmodule

module alu #(parameter WIDTH = 8)
            (input      [WIDTH-1:0] a, b, 
             input      [2:0]       alucont, 
             output reg [WIDTH-1:0] result);

   wire     [WIDTH-1:0] b2, sum, slt;

   assign b2 = alucont[2] ? ~b:b; 
   assign sum = a + b2 + alucont[2];
   // slt should be 1 if most significant bit of sum is 1
   assign slt = sum[WIDTH-1];

   always@(*)
      case(alucont[1:0])
         2'b00: result <= a & b;
         2'b01: result <= a | b;
         2'b10: result <= sum;
         2'b11: result <= slt;
      endcase
endmodule

module regfile #(parameter WIDTH = 8, REGBITS = 3)
                (input                clk, 
                 input                regwrite, 
                 input  [REGBITS-1:0] ra1, ra2, wa, 
                 input  [WIDTH-1:0]   wd, 
                 output [WIDTH-1:0]   rd1, rd2);

   reg  [WIDTH-1:0] RAM [(1<<REGBITS)-1:0];

   // three ported register file
   // read two ports combinationally
   // write third port on rising edge of clock
   // register 0 hardwired to 0
   always @(posedge clk)
      if (regwrite) RAM[wa] <= wd;	

   assign rd1 = ra1 ? RAM[ra1] : 0;
   assign rd2 = ra2 ? RAM[ra2] : 0;
endmodule

module zerodetect #(parameter WIDTH = 8)
                   (input [WIDTH-1:0] a, 
                    output            y);

   assign y = (a==0);
endmodule	

module flop #(parameter WIDTH = 8)
             (input                  clk, 
              input      [WIDTH-1:0] d, 
              output reg [WIDTH-1:0] q);

   always @(posedge clk)
      q <= d;
endmodule

module flopen #(parameter WIDTH = 8)
               (input                  clk, en,
                input      [WIDTH-1:0] d, 
                output reg [WIDTH-1:0] q);

   always @(posedge clk)
      if (en) q <= d;
endmodule

module flopenr #(parameter WIDTH = 8)
                (input                  clk, reset, en,
                 input      [WIDTH-1:0] d, 
                 output reg [WIDTH-1:0] q);
 
   always @(posedge clk)
      if      (reset) q <= 0;
      else if (en)    q <= d;
endmodule

module mux2 #(parameter WIDTH = 8)
             (input  [WIDTH-1:0] d0, d1, 
              input              s, 
              output [WIDTH-1:0] y);

   assign y = s ? d1 : d0; 
endmodule

module mux4 #(parameter WIDTH = 8)
             (input      [WIDTH-1:0] d0, d1, d2, d3,
              input      [1:0]       s, 
              output reg [WIDTH-1:0] y);

   always @(*)
      case(s)
         2'b00: y <= d0;
         2'b01: y <= d1;
         2'b10: y <= d2;
         2'b11: y <= d3;
      endcase
endmodule

mips32/sum32test.v
//-------------------------------------------------------
// mips.v
// Max Yi (byyi@hmc.edu) and David_Harris@hmc.edu 12/9/03
// Model of subset of MIPS processor described in Ch 1
//-------------------------------------------------------
`timescale 1ns/100ps

// top level design for testing
//Modified by matutani
//module top #(parameter WIDTH = 8, REGBITS = 3)();
module top #(parameter WIDTH = 32, REGBITS = 3)();
//

   reg                 clk;
   reg                 reset;
   wire                memread, memwrite;
   wire    [WIDTH-1:0] adr, writedata;
   wire    [WIDTH-1:0] memdata;

   // 5nsec --> 200MHz
   parameter STEP = 5.0;

   // instantiate devices to be tested
   //mips #(WIDTH,REGBITS) dut(clk, reset, memdata, memread, memwrite, adr, writedata);
   mips dut(clk, reset, memdata, memread, memwrite, adr, writedata);

   // external memory for code and data
   exmemory #(WIDTH) exmem(clk, memwrite, adr, writedata, memdata);

   // initialize test
   initial
      begin
         clk <= 0; reset <= 1; # 22; reset <= 0;
         // dump waveform
         $dumpfile("dump.vcd");
         $dumpvars(0, top.dut);
         // stop at 1,000 cycles
         #(STEP*1000);
         $finish;
      end

   // generate clock to sequence tests
   always #(STEP/2)
      begin
         clk <= ~clk;
      end

   always@(negedge clk)
      begin
         if(memwrite) begin
            $display("Data [%d] is stored in Address [%d]", writedata, adr);
            //Modified by matutani
            //if(adr == 5 & writedata == 7) begin
            if(adr == 252 & writedata == 210) begin
            //
               $display("Simulation completely successful");
               $finish;
            end else begin
               $display("Simulation failed");
               $finish;
            end
        end
      end
endmodule

// external memory accessed by MIPS
module exmemory #(parameter WIDTH = 8)
                 (clk, memwrite, adr, writedata, memdata);

   input                  clk;
   input                  memwrite;
   input      [WIDTH-1:0] adr, writedata;
   output reg [WIDTH-1:0] memdata;

   //Modified by matutani
   //reg  [31:0] RAM [(1<<WIDTH-2)-1:0];
   reg  [31:0] RAM [255:0];
   //
   wire [31:0] word;

   initial
      begin
         //Modified by matutani
         //$readmemh("mipstest.dat", RAM);
         $readmemh("sum32test.dat", RAM);
         //
      end

   // read and write bytes from 32-bit word
   always @(posedge clk)
      if(memwrite) 
         //Modified by matutani
         RAM[adr>>2][31:0] <= writedata;
         //case (adr[1:0])
         //   2'b00: RAM[adr>>2][7:0] <= writedata;
         //   2'b01: RAM[adr>>2][15:8] <= writedata;
         //   2'b10: RAM[adr>>2][23:16] <= writedata;
         //   2'b11: RAM[adr>>2][31:24] <= writedata;
         //endcase
         //

   assign word = RAM[adr>>2];
   always @(*)
     //Modified by matutani
     memdata <= word[31:0];
     // case (adr[1:0])
     //    2'b00: memdata <= word[31:24];
     //    2'b01: memdata <= word[23:16];
     //    2'b10: memdata <= word[15:8];
     //    2'b11: memdata <= word[7:0];
     // endcase
     //
endmodule

mips32/dump.vcd
$date
    Jul 20, 2017  16:42:29
$end
$version
    TOOL:	ncsim	06.20-s004
$end
$timescale
    100 ps
$end

$scope module top $end

$scope module dut $end
$var parameter 32 !    WIDTH  $end
$var parameter 32 "    REGBITS  $end
$var wire      1 #    clk  $end
$var wire      1 $    reset  $end
$var wire     32 %    memdata [31:0] $end
$var wire      1 &    memread  $end
$var wire      1 '    memwrite  $end
$var wire     32 (    adr [31:0] $end
$var wire     32 )    writedata [31:0] $end
$var wire     32 *    instr [31:0] $end
$var wire      1 +    zero  $end
$var wire      1 ,    alusrca  $end
$var wire      1 -    memtoreg  $end
$var wire      1 .    iord  $end
$var wire      1 /    pcen  $end
$var wire      1 0    regwrite  $end
$var wire      1 1    regdst  $end
$var wire      2 2    aluop [1:0] $end
$var wire      2 3    pcsource [1:0] $end
$var wire      2 4    alusrcb [1:0] $end
$var wire      1 5    irwrite [3] $end
$var wire      1 6    irwrite [2] $end
$var wire      1 7    irwrite [1] $end
$var wire      1 8    irwrite [0] $end
$var wire      3 9    alucont [2:0] $end

$scope module cont $end
$var wire      1 #    clk  $end
$var wire      1 $    reset  $end
$var wire      6 :    op [5:0] $end
$var wire      1 +    zero  $end
$var reg       1 ;    memread  $end
$var reg       1 <    memwrite  $end
$var reg       1 =    alusrca  $end
$var reg       1 >    memtoreg  $end
$var reg       1 ?    iord  $end
$var wire      1 /    pcen  $end
$var reg       1 @    regwrite  $end
$var reg       1 A    regdst  $end
$var reg       2 B    pcsource [1:0] $end
$var reg       2 C    alusrcb [1:0] $end
$var reg       2 D    aluop [1:0] $end
$var reg       4 E    irwrite [3:0] $end
$var parameter  4 F    FETCH1  $end
$var parameter  4 G    FETCH2  $end
$var parameter  4 H    FETCH3  $end
$var parameter  4 I    FETCH4  $end
$var parameter  4 J    DECODE  $end
$var parameter  4 K    MEMADR  $end
$var parameter  4 L    LBRD  $end
$var parameter  4 M    LBWR  $end
$var parameter  4 N    SBWR  $end
$var parameter  4 O    RTYPEEX  $end
$var parameter  4 P    RTYPEWR  $end
$var parameter  4 Q    BEQEX  $end
$var parameter  4 R    JEX  $end
$var parameter  4 S    ADDIEX  $end
$var parameter  4 T    ADDIWR  $end
$var parameter  6 U    LB  $end
$var parameter  6 V    SB  $end
$var parameter  6 W    LW  $end
$var parameter  6 X    SW  $end
$var parameter  6 Y    RTYPE  $end
$var parameter  6 Z    BEQ  $end
$var parameter  6 [    ADDI  $end
$var parameter  6 \    J  $end
$var reg       4 ]    state [3:0] $end
$var reg       4 ^    nextstate [3:0] $end
$var reg       1 _    pcwrite  $end
$var reg       1 `    pcwritecond  $end
$upscope $end


$scope module ac $end
$var wire      2 2    aluop [1:0] $end
$var wire      6 a    funct [5:0] $end
$var reg       3 b    alucont [2:0] $end
$upscope $end


$scope module dp $end
$var parameter 32 c    WIDTH  $end
$var parameter 32 d    REGBITS  $end
$var wire      1 #    clk  $end
$var wire      1 $    reset  $end
$var wire     32 %    memdata [31:0] $end
$var wire      1 ,    alusrca  $end
$var wire      1 -    memtoreg  $end
$var wire      1 .    iord  $end
$var wire      1 /    pcen  $end
$var wire      1 0    regwrite  $end
$var wire      1 1    regdst  $end
$var wire      2 3    pcsource [1:0] $end
$var wire      2 4    alusrcb [1:0] $end
$var wire      1 5    irwrite [3] $end
$var wire      1 6    irwrite [2] $end
$var wire      1 7    irwrite [1] $end
$var wire      1 8    irwrite [0] $end
$var wire      3 9    alucont [2:0] $end
$var wire      1 +    zero  $end
$var wire     32 *    instr [31:0] $end
$var wire     32 (    adr [31:0] $end
$var wire     32 )    writedata [31:0] $end
$var parameter 32 e    CONST_ZERO  $end
$var parameter 32 f    CONST_ONE  $end
$var parameter 32 g    CONST_FOUR  $end
$var wire      3 h    ra1 [2:0] $end
$var wire      3 i    ra2 [2:0] $end
$var wire      3 j    wa [2:0] $end
$var wire     32 k    pc [31:0] $end
$var wire     32 l    nextpc [31:0] $end
$var wire     32 m    md [31:0] $end
$var wire     32 n    rd1 [31:0] $end
$var wire     32 o    rd2 [31:0] $end
$var wire     32 p    wd [31:0] $end
$var wire     32 q    a [31:0] $end
$var wire     32 r    src1 [31:0] $end
$var wire     32 s    src2 [31:0] $end
$var wire     32 t    aluresult [31:0] $end
$var wire     32 u    aluout [31:0] $end
$var wire     32 v    constx4 [31:0] $end

$scope module regmux $end
$var parameter 32 w    WIDTH  $end
$var wire      3 x    d0 [2:0] $end
$var wire      3 y    d1 [2:0] $end
$var wire      1 1    s  $end
$var wire      3 j    y [2:0] $end
$upscope $end


$scope module ir3 $end
$var parameter 32 z    WIDTH  $end
$var wire      1 #    clk  $end
$var wire      1 5    en  $end
$var wire     32 %    d [31:0] $end
$var reg      32 {    q [31:0] $end
$upscope $end


$scope module pcreg $end
$var parameter 32 |    WIDTH  $end
$var wire      1 #    clk  $end
$var wire      1 $    reset  $end
$var wire      1 /    en  $end
$var wire     32 l    d [31:0] $end
$var reg      32 }    q [31:0] $end
$upscope $end


$scope module mdr $end
$var parameter 32 ~    WIDTH  $end
$var wire      1 #    clk  $end
$var wire     32 %    d [31:0] $end
$var reg      32 !!   q [31:0] $end
$upscope $end


$scope module areg $end
$var parameter 32 "!   WIDTH  $end
$var wire      1 #    clk  $end
$var wire     32 n    d [31:0] $end
$var reg      32 #!   q [31:0] $end
$upscope $end


$scope module wrd $end
$var parameter 32 $!   WIDTH  $end
$var wire      1 #    clk  $end
$var wire     32 o    d [31:0] $end
$var reg      32 %!   q [31:0] $end
$upscope $end


$scope module res $end
$var parameter 32 &!   WIDTH  $end
$var wire      1 #    clk  $end
$var wire     32 t    d [31:0] $end
$var reg      32 '!   q [31:0] $end
$upscope $end


$scope module adrmux $end
$var parameter 32 (!   WIDTH  $end
$var wire     32 k    d0 [31:0] $end
$var wire     32 u    d1 [31:0] $end
$var wire      1 .    s  $end
$var wire     32 (    y [31:0] $end
$upscope $end


$scope module src1mux $end
$var parameter 32 )!   WIDTH  $end
$var wire     32 k    d0 [31:0] $end
$var wire     32 q    d1 [31:0] $end
$var wire      1 ,    s  $end
$var wire     32 r    y [31:0] $end
$upscope $end


$scope module src2mux $end
$var parameter 32 *!   WIDTH  $end
$var wire     32 )    d0 [31:0] $end
$var wire     32 +!   d1 [31:0] $end
$var wire     32 ,!   d2 [31:0] $end
$var wire     32 v    d3 [31:0] $end
$var wire      2 4    s [1:0] $end
$var reg      32 -!   y [31:0] $end
$upscope $end


$scope module pcmux $end
$var parameter 32 .!   WIDTH  $end
$var wire     32 t    d0 [31:0] $end
$var wire     32 u    d1 [31:0] $end
$var wire     32 v    d2 [31:0] $end
$var wire     32 /!   d3 [31:0] $end
$var wire      2 3    s [1:0] $end
$var reg      32 0!   y [31:0] $end
$upscope $end


$scope module wdmux $end
$var parameter 32 1!   WIDTH  $end
$var wire     32 u    d0 [31:0] $end
$var wire     32 m    d1 [31:0] $end
$var wire      1 -    s  $end
$var wire     32 p    y [31:0] $end
$upscope $end


$scope module rf $end
$var parameter 32 2!   WIDTH  $end
$var parameter 32 3!   REGBITS  $end
$var wire      1 #    clk  $end
$var wire      1 0    regwrite  $end
$var wire      3 h    ra1 [2:0] $end
$var wire      3 i    ra2 [2:0] $end
$var wire      3 j    wa [2:0] $end
$var wire     32 p    wd [31:0] $end
$var wire     32 n    rd1 [31:0] $end
$var wire     32 o    rd2 [31:0] $end
$upscope $end


$scope module alunit $end
$var parameter 32 4!   WIDTH  $end
$var wire     32 r    a [31:0] $end
$var wire     32 s    b [31:0] $end
$var wire      3 9    alucont [2:0] $end
$var reg      32 5!   result [31:0] $end
$var wire     32 6!   b2 [31:0] $end
$var wire     32 7!   sum [31:0] $end
$var wire     32 8!   slt [31:0] $end
$upscope $end


$scope module zd $end
$var parameter 32 9!   WIDTH  $end
$var wire     32 t    a [31:0] $end
$var wire      1 +    y  $end
$upscope $end

$upscope $end

$upscope $end

$upscope $end

$enddefinitions $end
#220
$dumpvars
b100000 9!
b100000 4!
b11 3!
b100000 2!
b100000 1!
b100000 .!
b100000 *!
b100000 )!
b100000 (!
b100000 &!
b100000 $!
b100000 "!
b100000 ~
b100000 |
b100000 z
b11 w
b100 g
b1 f
b0 e
b11 d
b100000 c
b10 \
b1000 [
b100 Z
b0 Y
b101011 X
b100011 W
b101000 V
b100000 U
b1111 T
b1110 S
b1101 R
b1100 Q
b1011 P
b1010 O
b1001 N
b1000 M
b111 L
b110 K
b101 J
b100 I
b11 H
b10 G
b1 F
b11 "
b100000 !
0#
0$
b10001100000000100000000001000100 %
1&
0'
b0 (
bx )
b10001100000000100000000001000100 *
0+
0,
0-
0.
1/
00
01
b0 2
b0 3
b1 4
15
06
07
08
b10 9
b100011 :
1;
0<
0=
0>
0?
0@
0A
b0 B
b1 C
b0 D
b1000 E
b1 ]
b101 ^
1_
0`
b100 a
b10 b
b0 h
b10 i
b10 j
b0 k
b100 l
b10001100000000100000000001000100 m
b0 n
bx o
b100 p
b0 q
b0 r
b100 s
b100 t
b100 u
b100010000 v
b10 x
b0 y
b10001100000000100000000001000100 {
b0 }
b10001100000000100000000001000100 !!
b0 #!
bx %!
b100 '!
b100 +!
b1000100 ,!
b100 -!
b0 /!
b100 0!
b100 5!
b100 6!
b100 7!
b0 8!
$end
#225
1#
b100 }
b101 ]
b100 k
b100 (
b100 r
b1000 7!
b110 ^
b0 E
0_
0;
b11 C
b1000 5!
0/
b10001100000001110000000001000000 %
b1000 t
b11 4
0&
05
b1000 0!
b100010000 -!
b100010000 s
b1000 l
b100010000 6!
b100010100 7!
b100010100 5!
b100010100 t
b100010100 0!
b100010100 l
#250
0#
#275
1#
b100010100 '!
b10001100000001110000000001000000 !!
b110 ]
b10001100000001110000000001000000 m
b100010100 u
b100010100 p
b111 ^
b10 C
1=
1,
b10 4
b0 r
b100010000 7!
b1000100 -!
b100010000 5!
b100010000 t
b1000100 s
b1000100 6!
b1000100 7!
b100010000 0!
b1000100 5!
b1000100 t
b100010000 l
b1000100 0!
b1000100 l
#300
0#
#325
1#
b1000100 '!
b111 ]
b1000100 u
b1000100 p
b1000 ^
0=
b0 C
1;
1?
1.
1&
b0 4
0,
b100 r
b1000100 (
b1001000 7!
bx -!
b1001000 5!
b1001000 t
b101 %
bx s
bx 6!
bx 7!
b0x 8!
b1001000 0!
bx 5!
bx t
b1001000 l
x+
bx 0!
bx l
#350
0#
#375
1#
bx '!
b101 !!
b1000 ]
b101 m
bx u
bx (
bx p
b1 ^
0;
0?
1@
1>
bx %
1-
10
0.
0&
b100 (
b101 p
b10001100000001110000000001000000 %
#400
0#
#425
1#
b10001100000001110000000001000000 !!
b1 ]
b101 o
b10001100000001110000000001000000 m
b10001100000001110000000001000000 p
b101 ^
0@
0>
1;
b1000 E
b1 C
1_
1/
b1 4
15
1&
0-
00
bx p
b100 -!
b100 s
b100 6!
b1000 7!
b0 8!
b1000 5!
b1000 t
0+
b1000 0!
b1000 l
#450
0#
#475
1#
b1000 '!
b101 %!
b1000 }
b10001100000001110000000001000000 {
b101 ]
b10001100000001110000000001000000 *
b1000 k
b101 )
b1000 u
b1000 p
b1000 (
b1000 r
b0 a
b111 x
b1000000 ,!
b111 i
b100000000 v
bx o
b111 j
b1100 7!
b110 ^
b0 E
0_
0;
b11 C
b1100 5!
0/
b10001100000000110000000001001000 %
b1100 t
b11 4
0&
05
b1100 0!
b100000000 -!
b100000000 s
b1100 l
b100000000 6!
b100001000 7!
b100001000 5!
b100001000 t
b100001000 0!
b100001000 l
#500
0#
#525
1#
b100001000 '!
bx %!
b10001100000000110000000001001000 !!
b110 ]
b10001100000000110000000001001000 m
bx )
b100001000 u
b100001000 p
b111 ^
b10 C
1=
1,
b10 4
b0 r
b100000000 7!
b1000000 -!
b100000000 5!
b100000000 t
b1000000 s
b1000000 6!
b1000000 7!
b100000000 0!
b1000000 5!
b1000000 t
b100000000 l
b1000000 0!
b1000000 l
#550
0#
#575
1#
b1000000 '!
b111 ]
b1000000 u
b1000000 p
b1000 ^
0=
b0 C
1;
1?
1.
1&
b0 4
0,
b1000 r
b1000000 (
b1001000 7!
bx -!
b1001000 5!
b1001000 t
b11 %
bx s
bx 6!
bx 7!
b0x 8!
b1001000 0!
bx 5!
bx t
b1001000 l
x+
bx 0!
bx l
#600
0#
#625
1#
bx '!
b11 !!
b1000 ]
b11 m
bx u
bx (
bx p
b1 ^
0;
0?
1@
1>
bx %
1-
10
0.
0&
b1000 (
b11 p
b10001100000000110000000001001000 %
#650
0#
#675
1#
b10001100000000110000000001001000 !!
b1 ]
b11 o
b10001100000000110000000001001000 m
b10001100000000110000000001001000 p
b101 ^
0@
0>
1;
b1000 E
b1 C
1_
1/
b1 4
15
1&
0-
00
bx p
b100 -!
b100 s
b100 6!
b1100 7!
b0 8!
b1100 5!
b1100 t
0+
b1100 0!
b1100 l
#700
0#
#725
1#
b1100 '!
b11 %!
b1100 }
b10001100000000110000000001001000 {
b101 ]
b10001100000000110000000001001000 *
b1100 k
b11 )
b1100 u
b1100 p
b1100 (
b1100 r
b1000 a
b11 x
b1001000 ,!
b11 i
b100100000 v
bx o
b11 j
b10000 7!
b110 ^
b0 E
0_
0;
b11 C
b10000 5!
0/
b111000100010000000100101 %
b10000 t
b11 4
0&
05
b10000 0!
b100100000 -!
b100100000 s
b10000 l
b100100000 6!
b100101100 7!
b100101100 5!
b100101100 t
b100101100 0!
b100101100 l
#750
0#
#775
1#
b100101100 '!
bx %!
b111000100010000000100101 !!
b110 ]
b111000100010000000100101 m
bx )
b100101100 u
b100101100 p
b111 ^
b10 C
1=
1,
b10 4
b0 r
b100100000 7!
b1001000 -!
b100100000 5!
b100100000 t
b1001000 s
b1001000 6!
b1001000 7!
b100100000 0!
b1001000 5!
b1001000 t
b100100000 l
b1001000 0!
b1001000 l
#800
0#
#825
1#
b1001000 '!
b111 ]
b1001000 u
b1001000 p
b1000 ^
0=
b0 C
1;
1?
1.
1&
b0 4
0,
b1100 r
b1001000 (
b1010100 7!
bx -!
b1010100 5!
b1010100 t
b1100 %
bx s
bx 6!
bx 7!
b0x 8!
b1010100 0!
bx 5!
bx t
b1010100 l
x+
bx 0!
bx l
#850
0#
#875
1#
bx '!
b1100 !!
b1000 ]
b1100 m
bx u
bx (
bx p
b1 ^
0;
0?
1@
1>
bx %
1-
10
0.
0&
b1100 (
b1100 p
b111000100010000000100101 %
#900
0#
#925
1#
b111000100010000000100101 !!
b1 ]
b1100 o
b111000100010000000100101 m
b111000100010000000100101 p
b101 ^
0@
0>
1;
b1000 E
b1 C
1_
1/
b1 4
15
1&
0-
00
bx p
b100 -!
b100 s
b100 6!
b10000 7!
b0 8!
b10000 5!
b10000 t
0+
b10000 0!
b10000 l
#950
0#
#975
1#
b10000 '!
b1100 %!
b10000 }
b111000100010000000100101 {
b101 ]
b111000100010000000100101 *
b10000 k
b1100 )
b10000 u
b10000 p
b10000 (
b10000 r
b0 :
b100101 a
b10 x
b100 y
b10000000100101 ,!
b10 i
b111 h
b1000000010010100 v
b11 n
b101 o
b10 j
b10100 7!
b1010 ^
b0 E
0_
0;
b11 C
b10100 5!
0/
b11001000010100000100100 %
b10100 t
b11 4
0&
05
b10100 0!
b1000000010010100 -!
b1000000010010100 s
b10100 l
b1000000010010100 6!
b1000000010100100 7!
b1000000010100100 5!
b1000000010100100 t
b1000000010100100 0!
b1000000010100100 l
#1000
0#
